{"stat.useItem.minecraft.string":1,"stat.leaveGame":16,"stat.mineBlock.minecraft.cobblestone":19,"stat.swimOneCm":4789,"stat.useItem.minecraft.planks":270,"stat.climbOneCm":5091,"achievement.buildWorkBench":2,"stat.useItem.minecraft.dirt":45,"achievement.exploreAllBiomes":{"value":0,"progress":["Sunflower Plains","Savanna Plateau M","Forest","Plains","Desert","Savanna"]},"stat.craftItem.minecraft.furnace":3,"stat.useItem.minecraft.egg":2,"stat.craftItem.minecraft.stone_axe":2,"stat.craftItem.minecraft.trapdoor":2,"stat.craftItem.minecraft.stone_pickaxe":4,"stat.useItem.minecraft.stone_shovel":164,"stat.flyOneCm":50290,"achievement.buildPickaxe":10,"achievement.buildBetterPickaxe":8,"stat.mineBlock.minecraft.iron_ore":6,"stat.timeSinceDeath":43148,"stat.useItem.minecraft.iron_pickaxe":148,"stat.craftItem.minecraft.wooden_pickaxe":1,"stat.useItem.minecraft.oak_stairs":6,"stat.furnaceInteraction":17,"stat.useItem.minecraft.cooked_porkchop":5,"stat.mineBlock.minecraft.coal_ore":74,"stat.useItem.minecraft.double_plant":1,"stat.entityKilledBy.Skeleton":1,"achievement.mineWood":152,"stat.useItem.minecraft.trapdoor":1,"stat.sprintOneCm":33901,"stat.craftItem.minecraft.stick":36,"achievement.openInventory":58,"stat.mineBlock.minecraft.crafting_table":4,"stat.mineBlock.minecraft.oak_stairs":2,"achievement.buildFurnace":3,"stat.deaths":2,"stat.mineBlock.minecraft.planks":55,"stat.playOneMinute":256773,"stat.killEntity.Sheep":1,"stat.useItem.minecraft.ladder":4,"stat.craftItem.minecraft.iron_pickaxe":1,"stat.killEntity.Zombie":3,"stat.mineBlock.minecraft.tallgrass":36,"stat.diveOneCm":628,"stat.chestOpened":25,"stat.craftItem.minecraft.ladder":6,"stat.useItem.minecraft.stone":33,"stat.craftItem.minecraft.cooked_porkchop":5,"stat.craftItem.minecraft.coal":4,"stat.jump":576,"stat.fallOneCm":6818,"stat.useItem.minecraft.stone_axe":205,"stat.crouchOneCm":63766,"stat.mineBlock.minecraft.chest":14,"stat.craftItem.minecraft.iron_ingot":6,"stat.craftItem.minecraft.chest":12,"stat.useItem.minecraft.cooked_chicken":3,"stat.craftingTableInteraction":22,"stat.useItem.minecraft.sapling":16,"stat.damageTaken":920,"stat.mineBlock.minecraft.torch":2,"stat.mineBlock.minecraft.furnace":4,"stat.useItem.minecraft.wooden_pickaxe":3,"stat.useItem.minecraft.furnace":7,"stat.entityKilledBy.Zombie":1,"stat.useItem.minecraft.stone_pickaxe":511,"stat.breakItem.minecraft.stone_axe":1,"stat.damageDealt":3580,"stat.craftItem.minecraft.oak_stairs":4,"stat.killEntity.Cow":7,"stat.useItem.minecraft.crafting_table":6,"stat.mineBlock.minecraft.dirt":158,"stat.killEntity.Pig":7,"stat.craftItem.minecraft.stone_shovel":2,"stat.walkOneCm":641418,"stat.useItem.minecraft.chest":26,"stat.useItem.minecraft.log":70,"stat.useItem.minecraft.cobblestone":95,"stat.craftItem.minecraft.crafting_table":2,"stat.mineBlock.minecraft.double_plant":3,"stat.breakItem.minecraft.stone_pickaxe":4,"stat.breakItem.minecraft.stone_shovel":1,"stat.killEntity.Skeleton":2,"stat.craftItem.minecraft.planks":356,"stat.killEntity.Spider":1,"stat.mobKills":21,"stat.mineBlock.minecraft.log":163,"stat.craftItem.minecraft.wooden_door":3,"stat.craftItem.minecraft.cooked_chicken":35,"stat.useItem.minecraft.wooden_door":2,"stat.mineBlock.minecraft.leaves":60,"stat.craftItem.minecraft.coal_block":1,"stat.mineBlock.minecraft.stone":534}